README.txt
setup.py
geetakeout/__init__.py
geetakeout/geckodriver
geetakeout/geckodriver.exe
geetakeout/gee_assetcopy.py
geetakeout/gee_permissions.py
geetakeout/gee_replicate.py
geetakeout/gee_report.py
geetakeout/geetakeout.py
geetakeout/git_copy.py
geetakeout/git_geerepolist.py
geetakeout/git_password.py
geetakeout/git_replicate.py
geetakeout/git_repocreate.py
geetakeout/git_swap.py
geetakeout/sel-latest-linux.py
geetakeout/sel-latest-win.py
geetakeout.egg-info/PKG-INFO
geetakeout.egg-info/SOURCES.txt
geetakeout.egg-info/dependency_links.txt
geetakeout.egg-info/entry_points.txt
geetakeout.egg-info/requires.txt
geetakeout.egg-info/top_level.txt